maiconverter/__init__.py
maiconverter/__main__.py
maiconverter/cli.py
maiconverter/converter/__init__.py
maiconverter/converter/maima2tomaisxt.py
maiconverter/converter/maima2tosimai.py
maiconverter/converter/maisxttomaima2.py
maiconverter/converter/maisxttosimai.py
maiconverter/converter/simaitomaima2.py
maiconverter/converter/simaitomaisxt.py
maiconverter/event/__init__.py
maiconverter/event/event.py
maiconverter/event/note.py
maiconverter/maicrypt/__init__.py
maiconverter/maicrypt/maifinalecrypt.py
maiconverter/maima2/__init__.py
maiconverter/maima2/ma2note.py
maiconverter/maima2/maima2.py
maiconverter/maima2/tools.py
maiconverter/maisxt/__init__.py
maiconverter/maisxt/maisxt.py
maiconverter/maisxt/sxtchart.py
maiconverter/maisxt/sxtnote.py
maiconverter/simai/__init__.py
maiconverter/simai/simai.lark
maiconverter/simai/simai.py
maiconverter/simai/simai_fragment.lark
maiconverter/simai/simai_parser.py
maiconverter/simai/simainote.py
maiconverter/simai/tools.py
maiconverter/tool/__init__.py
maiconverter/tool/slide.py
maiconverter/tool/time.py
MaiConverter-0.14.5.dist-info/LICENSE
MaiConverter-0.14.5.dist-info/METADATA
MaiConverter-0.14.5.dist-info/WHEEL
MaiConverter-0.14.5.dist-info/entry_points.txt
MaiConverter-0.14.5.dist-info/top_level.txt
MaiConverter-0.14.5.dist-info/RECORD
