Metadata-Version: 2.1
Name: MaiConverter
Version: 0.14.5
Summary: Parse and convert Maimai chart formats
Home-page: https://github.com/donmai-me/MaiConverter
Author: donmai
License: UNKNOWN
Platform: UNKNOWN
Classifier: Programming Language :: Python :: 3
Classifier: Programming Language :: Python :: 3.8
Classifier: License :: OSI Approved :: MIT License
Classifier: Operating System :: OS Independent
Classifier: Development Status :: 4 - Beta
Classifier: Intended Audience :: Other Audience
Classifier: Topic :: Games/Entertainment :: Arcade
Requires-Python: ~=3.8
License-File: LICENSE
Requires-Dist: pycryptodome (~=3.9)
Requires-Dist: lark-parser (~=0.11)
